sony_custom_layers/__init__.py
sony_custom_layers/version.py
sony_custom_layers/common/__init__.py
sony_custom_layers/common/box_util.py
sony_custom_layers/keras/__init__.py
sony_custom_layers/keras/base_custom_layer.py
sony_custom_layers/keras/custom_objects.py
sony_custom_layers/keras/object_detection/__init__.py
sony_custom_layers/keras/object_detection/faster_rcnn_box_decode.py
sony_custom_layers/keras/object_detection/score_converter.py
sony_custom_layers/keras/object_detection/ssd_post_process.py
sony_custom_layers/pytorch/__init__.py
sony_custom_layers/pytorch/custom_lib.py
sony_custom_layers/pytorch/box_decode/__init__.py
sony_custom_layers/pytorch/box_decode/box_decode.py
sony_custom_layers/pytorch/box_decode/box_decode_onnx.py
sony_custom_layers/pytorch/box_decode/box_decode_ort.py
sony_custom_layers/pytorch/nms/__init__.py
sony_custom_layers/pytorch/nms/nms.py
sony_custom_layers/pytorch/nms/nms_common.py
sony_custom_layers/pytorch/nms/nms_onnx.py
sony_custom_layers/pytorch/nms/nms_ort.py
sony_custom_layers/pytorch/nms/nms_with_indices.py
sony_custom_layers/util/__init__.py
sony_custom_layers/util/import_util.py
sony_custom_layers/util/test_util.py
sony_custom_layers-0.3.0.dist-info/LICENSE.md
sony_custom_layers-0.3.0.dist-info/METADATA
sony_custom_layers-0.3.0.dist-info/WHEEL
sony_custom_layers-0.3.0.dist-info/top_level.txt
sony_custom_layers-0.3.0.dist-info/RECORD
