Metadata-Version: 2.2
Name: sony-custom-layers
Version: 0.3.0
Summary: Sony Custom Layers package
Classifier: Programming Language :: Python :: 3
Classifier: License :: OSI Approved :: Apache Software License
Classifier: Operating System :: OS Independent
Classifier: Topic :: Scientific/Engineering :: Artificial Intelligence
Requires-Python: <3.12,>=3.8
License-File: LICENSE.md
Requires-Dist: numpy<2
Requires-Dist: packaging
Provides-Extra: torch
Requires-Dist: torch==2.4.*; extra == "torch"
Requires-Dist: torchvision==0.19.*; extra == "torch"
Requires-Dist: onnx==1.16.*; extra == "torch"
Requires-Dist: onnxruntime==1.19.*; extra == "torch"
Requires-Dist: onnxruntime_extensions==0.12.*; extra == "torch"
Provides-Extra: tf
Requires-Dist: tensorflow==2.15.*; extra == "tf"
Dynamic: provides-extra
